setup.cfg
setup.py
multiget_cache/__init__.py
multiget_cache/base_cache_wrapper.py
multiget_cache/cache_interface.py
multiget_cache/flask_request_cache.py
multiget_cache/function_tools.py
multiget_cache/multiget_cache_wrapper.py
multiget_cache.egg-info/PKG-INFO
multiget_cache.egg-info/SOURCES.txt
multiget_cache.egg-info/dependency_links.txt
multiget_cache.egg-info/top_level.txt
multiget_cache.egg-info/zip-safe
test/__init__.py
test/test_end_to_end.py