Metadata-Version: 1.0
Name: multiget-cache
Version: 0.0.10
Summary: Python library for turning N function calls into 1 memoized call. Especially useful for SQL optimization.
Home-page: http://github.com/Patreon/multiget-cache-py
Author: Patreon
Author-email: zach@patreon.com
License: MIT
Platform: UNKNOWN
